{
  "latest": "1.64.9",
  "versions": [
    {
      "version": "1.64.9",
      "status": "published",
      "releaseDate": "2026-05-30",
      "platforms": {
        "server": {
          "version": "1.64.3",
          "notes": "语音对话延迟优化hotfix"
        }
      },
      "releaseNotes": "v1.64.9 - 语音对话延迟优化全链路部署",
      "features": [
        "Fix: faster-whisper tiny int8 STT推理加速(5s音频<0.5s, 原3-6s)",
        "Fix: 每阶段超时保护(STT 10s/AI 15s/TTS 8s)",
        "Fix: TTS缓存预热6条高频短语(启动即就绪)",
        "Fix: 流式ASR滑动窗口3s→2s, interim间隔1s→0.5s",
        "Fix: 移除faster-whisper不兼容参数(logprob_threshold/no_speech_threshold)",
        "Fix: 生产服务器PostgreSQL+TTS预热(ffmpeg)配置"
      ]
    },
    {
      "version": "1.64.3",
      "status": "published",
      "releaseDate": "2026-05-30",
      "platforms": {
        "server": {
          "version": "1.64.3",
          "notes": "hotfix: 移除faster-whisper不兼容参数 + 生产环境配置"
        }
      },
      "releaseNotes": "v1.64.3 - 语音对话延迟优化hotfix",
      "features": [
        "Fix: 移除faster-whisper不兼容参数 (logprob_threshold/no_speech_threshold)",
        "Fix: 生产服务器PostgreSQL安装配置 + 服务启动",
        "Fix: 生产服务器TTS预热(安装ffmpeg)",
        "Fix: 前端TS类型修复(revertFile)",
        "New: faster-whisper tiny int8 推理<0.5s/5s音频"
      ]
    },
    {
      "version": "1.64.2",
      "status": "published",
      "releaseDate": "2026-05-30",
      "platforms": {
        "win-x64": {
          "url": "/downloads/LingJing-Setup-1.64.2-win-x64.exe",
          "size": 142209962
        },
        "win-x64-portable": {
          "url": "/downloads/LingJing-Portable-1.64.2-win-x64.exe",
          "size": 141868430
        },
        "win-x64-blockmap": {
          "url": "/downloads/LingJing-Setup-1.64.2-win-x64.exe.blockmap",
          "size": 160729
        },
        "linux-x64": {
          "url": "/downloads/LingJing-1.64.2-linux-x86_64.AppImage",
          "size": 158000000
        },
        "mobile": {
          "url": "/downloads/lingjing-mobile-v1.60.1.apk",
          "size": 39044682
        }
      },
      "releaseNotes": "v1.64.2 - Fix 4 issues",
      "features": [
        "Fix: Downloads page shows all platforms (was only Android)",
        "Fix: Auto-compaction no longer interrupts running tasks",
        "Fix: Cannot read properties of undefined (reading 'map') error",
        "Fix: Todo list always shows empty placeholder"
      ]
    },
    {
      "version": "1.64.1",
      "status": "published",
      "releaseDate": "2026-05-30",
      "platforms": {
        "win-x64": {
          "url": "/downloads/LingJing-Setup-1.64.1-win-x64.exe",
          "size": 142211624
        },
        "win-x64-portable": {
          "url": "/downloads/LingJing-Portable-1.64.1-win-x64.exe",
          "size": 141870121
        },
        "win-x64-blockmap": {
          "url": "/downloads/LingJing-Setup-1.64.1-win-x64.exe.blockmap",
          "size": 148665
        },
        "linux-x64": {
          "url": "/downloads/LingJing-1.64.1-linux-x86_64.AppImage",
          "size": 155978785
        },
        "linux-deb": {
          "url": "/downloads/LingJing-1.64.1-linux-x86_64.deb",
          "size": 110990662
        },
        "mobile": {
          "url": "/downloads/lingjing-mobile-v1.60.1.apk",
          "size": 39044682
        }
      },
      "releaseNotes": "v1.64.1 - Fix Cannot read properties of undefined (reading 'ipcRenderer')",
      "features": [
        "Fix: Expose window.electron.ipcRenderer compatibility layer"
      ]
    },
    {
      "version": "1.64.0",
      "status": "published",
      "releaseDate": "2026-05-30",
      "platforms": {
        "win-x64": {
          "url": "/downloads/LingJing-Setup-1.64.0-win-x64.exe",
          "size": 142208922
        },
        "win-x64-portable": {
          "url": "/downloads/LingJing-Portable-1.64.0-win-x64.exe",
          "size": 141867366
        },
        "win-x64-blockmap": {
          "url": "/downloads/LingJing-Setup-1.64.0-win-x64.exe.blockmap",
          "size": 149744
        },
        "linux-x64": {
          "url": "/downloads/LingJing-1.64.0-linux-x86_64.AppImage",
          "size": 183533834
        },
        "linux-deb": {
          "url": "/downloads/LingJing-1.64.0-linux-x86_64.deb",
          "size": 110968034
        },
        "mobile": {
          "url": "/downloads/lingjing-mobile-v1.60.1.apk",
          "size": 39044682
        }
      },
      "releaseNotes": "v1.64.0 - Fix file auto-processing not working (3 root causes)",
      "features": [
        "Fix: QuestConversation race condition auto-accept/reject not working",
        "Fix: PipelineService using wrong directory to init",
        "Fix: Switch workspace PipelineService not auto-loading pipelines"
      ]
    },
    {
      "version": "1.63.0",
      "status": "published",
      "releaseDate": "2026-05-30",
      "platforms": {
        "win-x64": {
          "url": "/downloads/LingJing-Setup-1.63.0-win-x64.exe",
          "size": 142209253
        },
        "win-x64-portable": {
          "url": "/downloads/LingJing-Portable-1.63.0-win-x64.exe",
          "size": 141867721
        },
        "win-x64-blockmap": {
          "url": "/downloads/LingJing-Setup-1.63.0-win-x64.exe.blockmap",
          "size": 148752
        },
        "linux-x64": {
          "url": "/downloads/LingJing-1.63.0-linux-x86_64.AppImage",
          "size": 183533943
        },
        "mobile": {
          "url": "/downloads/lingjing-mobile-v1.60.1.apk",
          "size": 39044682
        }
      },
      "releaseNotes": "v1.63.0",
      "features": [
        "Fix: File auto-processing (Pipeline Watch Trigger)",
        "Fix: registerPipelineIPC not registered",
        "Fix: TriggerManager not linked to PipelineService",
        "New: Add watch file auto-processing support",
        "New: Auto-load .lingjing/pipelines/*.yaml"
      ]
    },
    {
      "version": "1.62.3",
      "status": "published",
      "releaseDate": "2026-05-30",
      "platforms": {
        "win-x64": {
          "url": "/downloads/LingJing-Setup-1.62.3-win-x64.exe",
          "size": 142204523
        },
        "win-x64-portable": {
          "url": "/downloads/LingJing-Portable-1.62.3-win-x64.exe",
          "size": 141863003
        },
        "win-x64-blockmap": {
          "url": "/downloads/LingJing-Setup-1.62.3-win-x64.exe.blockmap",
          "size": 148752
        }
      },
      "releaseNotes": "v1.62.3",
      "features": [
        "Fix: TodoTracker missing in streaming responses",
        "Fix: Todo persistence across task switches",
        "Fix: Empty todo list now shows placeholder"
      ]
    },
    {
      "version": "1.62.0",
      "status": "published",
      "releaseDate": "2026-05-29",
      "platforms": {
        "win-x64": {
          "url": "/downloads/LingJing-Setup-1.62.0-win-x64.exe",
          "size": 142204585
        },
        "win-x64-portable": {
          "url": "/downloads/LingJing-Portable-1.62.0-win-x64.exe",
          "size": 141863065
        },
        "win-x64-blockmap": {
          "url": "/downloads/LingJing-Setup-1.62.0-win-x64.exe.blockmap",
          "size": 148904
        },
        "linux-x64": {
          "url": "/downloads/LingJing-1.62.0-linux-x86_64.AppImage",
          "size": 184549376
        },
        "linux-deb": {
          "url": "/downloads/LingJing-1.62.0-linux-x86_64.deb",
          "size": 212000000
        },
        "mobile": {
          "url": "/downloads/lingjing-mobile-v1.60.1.apk",
          "size": 39044682
        }
      },
      "releaseNotes": "v1.62.0",
      "features": [
        "Fix A-G: conversation fixes"
      ]
    },
    {
      "version": "1.61.1",
      "status": "published",
      "releaseDate": "2026-05-29",
      "platforms": {
        "win-x64": {
          "url": "/downloads/LingJing-Setup-1.61.1-win-x64.exe",
          "size": 142200287
        },
        "win-x64-portable": {
          "url": "/downloads/LingJing-Portable-1.61.1-win-x64.exe",
          "size": 141858740
        },
        "linux-x64": {
          "url": "/downloads/LingJing-1.61.1-linux-x86_64.AppImage",
          "size": 183533011
        },
        "mobile": {
          "url": "/downloads/lingjing-mobile-v1.60.1.apk",
          "size": 39044682
        }
      },
      "releaseNotes": "v1.61.1: fix blank page"
    },
    {
      "version": "1.61.0",
      "status": "published",
      "releaseDate": "2026-05-29",
      "platforms": {
        "linux-x64": {
          "url": "/downloads/LingJing-1.61.0-linux-x86_64.AppImage",
          "size": 183533038
        },
        "win-x64": {
          "url": "/downloads/LingJing-Setup-1.61.0-win-x64.exe",
          "size": 142021614
        },
        "win-x64-portable": {
          "url": "/downloads/LingJing-Portable-1.61.0-win-x64.exe",
          "size": 141680103
        },
        "mobile": {
          "url": "/downloads/lingjing-mobile-v1.60.1.apk",
          "size": 39044682
        }
      }
    }
  ]
}